simple_hdlc/example.py
simple_hdlc/simple_hdlc.py
simple_hdlc/test_hdlc.py
simple_hdlc-0.2.dist-info/DESCRIPTION.rst
simple_hdlc-0.2.dist-info/METADATA
simple_hdlc-0.2.dist-info/RECORD
simple_hdlc-0.2.dist-info/WHEEL
simple_hdlc-0.2.dist-info/metadata.json
simple_hdlc-0.2.dist-info/top_level.txt
