Metadata-Version: 2.0
Name: simple-hdlc
Version: 0.2
Summary: Simple HDLC Protocol
Home-page: https://github.com/wuttem/simple-hdlc
Author: Matthias Wutte
Author-email: matthias.wutte@gmail.com
License: UNKNOWN
Keywords: simple-hdlc
Platform: UNKNOWN
Requires-Dist: pyserial
Requires-Dist: pycrc
